binance/__init__.py
binance/__init__.pyi
binance/main.py
binance/margin.py
binance/simple_earn.py
binance/user.py
binance/user_stream.py
binance/wallet.py
binance/simple_earn/__init__.py
binance/simple_earn/__init__.pyi
binance/simple_earn/simple_earn.py
binance/simple_earn/account/__init__.py
binance/simple_earn/account/_account.py
binance/simple_earn/account/_flexible_position.py
binance/simple_earn/account/_flexible_products.py
binance/simple_earn/account/_flexible_quota.py
binance/simple_earn/account/_locked_position.py
binance/simple_earn/account/_locked_products.py
binance/simple_earn/account/_locked_quota.py
binance/simple_earn/account/account.py
binance/simple_earn/earn/__init__.py
binance/simple_earn/earn/_flexible_preview.py
binance/simple_earn/earn/_flexible_redeem.py
binance/simple_earn/earn/_flexible_subscribe.py
binance/simple_earn/earn/earn.py
binance/spot/__init__.py
binance/spot/__init__.pyi
binance/spot/spot.py
binance/spot/account/__init__.py
binance/spot/account/_info.py
binance/spot/account/_trades.py
binance/spot/account/account.py
binance/spot/account/test_account.py
binance/spot/data/__init__.py
binance/spot/data/_avg_price.py
binance/spot/data/_candles.py
binance/spot/data/_candles_ui.py
binance/spot/data/_order_book.py
binance/spot/data/_price.py
binance/spot/data/_stats.py
binance/spot/data/_stats_24h.py
binance/spot/data/_stats_day.py
binance/spot/data/_trades_agg.py
binance/spot/data/_trades_old.py
binance/spot/data/_trades_recent.py
binance/spot/data/data.py
binance/spot/data/test_data.py
binance/spot/general/__init__.py
binance/spot/general/_info.py
binance/spot/general/_ping.py
binance/spot/general/_time.py
binance/spot/general/general.py
binance/spot/general/test_general.py
binance/spot/trading/__init__.py
binance/spot/trading/_cancel_open_orders.py
binance/spot/trading/_cancel_order.py
binance/spot/trading/_cancel_order_list.py
binance/spot/trading/_new_order.py
binance/spot/trading/_oco_order.py
binance/spot/trading/_oto_order.py
binance_python-0.2.2.dist-info/METADATA
binance_python-0.2.2.dist-info/WHEEL
binance_python-0.2.2.dist-info/top_level.txt
binance_python-0.2.2.dist-info/RECORD
