Metadata-Version: 2.2
Name: binance-python
Version: 0.2.2
Summary: Python Binance API client, with typings.
Author-email: Marcel Claramunt <marcel@marcelc.uk>
Project-URL: repo, https://github.com/tribulnation/binance.git
Requires-Python: >=3.10
Requires-Dist: pydantic
Requires-Dist: httpx
Requires-Dist: websockets
Requires-Dist: haskellian
Requires-Dist: orjson
Requires-Dist: lazy-loader
